README.md
setup.py
foreutils/__init__.py
foreutils/denoising.py
foreutils/fault_detection.py
foreutils/forecasting.py
foreutils/metrics.py
foreutils/utils.py
foreutils/visualization.py
foreutils.egg-info/PKG-INFO
foreutils.egg-info/SOURCES.txt
foreutils.egg-info/dependency_links.txt
foreutils.egg-info/top_level.txt