Metadata-Version: 2.1
Name: foreutils
Version: 0.1.0
Summary: Utilities for signal forecasting of satelite images with echo-state networks (ESN)
Author: Tomás Couso Coddou
Author-email: tomascousocoddou@gmail.com
Classifier: Programming Language :: Python :: 3
Classifier: License :: OSI Approved :: MIT License
Classifier: Operating System :: OS Independent
Requires-Python: >=3.6
